README.md
setup.py
graphly/__init__.py
graphly/edge.py
graphly/graph.py
graphly/node.py
graphly.egg-info/PKG-INFO
graphly.egg-info/SOURCES.txt
graphly.egg-info/dependency_links.txt
graphly.egg-info/requires.txt
graphly.egg-info/top_level.txt
graphly/algorithm/__init__.py
graphly/algorithm/algorithm.py
graphly/factory/__init__.py
graphly/factory/factory.py
graphly/generator/__init__.py
graphly/generator/generator.py
graphly/plotter/__init__.py
graphly/plotter/plotter.py
graphly/reader/__init__.py
graphly/reader/reader.py
graphly/representation/__init__.py
graphly/representation/representation.py